vikingzero/__init__.py
vikingzero/agents/__init__.py
vikingzero/agents/alphago.py
vikingzero/agents/connect4_agent.py
vikingzero/agents/tictactoe_agents.py
vikingzero/connect4_uci_test.py
vikingzero/designer.py
vikingzero/environments/__init__.py
vikingzero/environments/connect4_env.py
vikingzero/environments/tictactoe_env.py
vikingzero/run_agent.py
vikingzero/search.py
vikingzero/utils.py
vikingzero-0.1.3.dist-info/WHEEL
vikingzero-0.1.3.dist-info/METADATA
vikingzero-0.1.3.dist-info/RECORD
