Metadata-Version: 2.1
Name: vikingzero
Version: 0.1.3
Summary: 
Author: David SeWell
Author-email: davidsewell3145@gmail.com
Requires-Python: >=3.6.2,<4.0.0
Classifier: Programming Language :: Python :: 3
Classifier: Programming Language :: Python :: 3.7
Classifier: Programming Language :: Python :: 3.8
Classifier: Programming Language :: Python :: 3.9
Requires-Dist: PyYAML
Requires-Dist: matplotlib
Requires-Dist: numpy (>=1.15.4,<2.0.0)
Requires-Dist: tensorboard
Requires-Dist: tensorboardX (>=2.1,<3.0)
Requires-Dist: torch (==1.7.1)
Requires-Dist: tqdm
